imcode
