Metadata-Version: 2.1
Name: imcode
Version: 0.1.1
Summary: ImCode - Run codeserver on Colab!
Home-page: https://github.com/imneonizer/imcode
Author: Nitin Rai
Author-email: mneonizer@gmail.com
License: MIT License
Platform: linux
Platform: unix
Requires-Python: >3.5.2
